[
  {
    "word": "بعد",
    "start": 0.03,
    "end": 0.53
  },
  {
    "word": "موقعة",
    "start": 0.55,
    "end": 1.17
  },
  {
    "word": "الجسر",
    "start": 1.21,
    "end": 1.69
  },
  {
    "word": "التي",
    "start": 1.73,
    "end": 2.07
  },
  {
    "word": "كانت",
    "start": 2.17,
    "end": 2.65
  },
  {
    "word": "لها",
    "start": 2.71,
    "end": 3.11
  },
  {
    "word": "أثر",
    "start": 3.19,
    "end": 3.61
  },
  {
    "word": "كبير",
    "start": 3.73,
    "end": 4.38
  },
  {
    "word": "على",
    "start": 4.43,
    "end": 4.74
  },
  {
    "word": "مجرى",
    "start": 4.83,
    "end": 5.18
  },
  {
    "word": "الفتوح",
    "start": 5.22,
    "end": 6.36
  },
  {
    "word": "وفي",
    "start": 6.54,
    "end": 6.8
  },
  {
    "word": "نهاية",
    "start": 6.88,
    "end": 7.36
  },
  {
    "word": "السنة",
    "start": 7.38,
    "end": 7.82
  },
  {
    "word": "الثالثة",
    "start": 7.86,
    "end": 8.54
  },
  {
    "word": "عشرة",
    "start": 8.68,
    "end": 9.22
  },
  {
    "word": "للهجرة",
    "start": 9.28,
    "end": 10.5
  },
  {
    "word": "توجه",
    "start": 10.6,
    "end": 11.08
  },
  {
    "word": "خالد",
    "start": 11.18,
    "end": 11.54
  },
  {
    "word": "بن",
    "start": 11.58,
    "end": 11.68
  },
  {
    "word": "الوليد",
    "start": 11.72,
    "end": 12.74
  },
  {
    "word": "رضي",
    "start": 12.86,
    "end": 13.14
  },
  {
    "word": "الله",
    "start": 13.16,
    "end": 13.58
  },
  {
    "word": "عنه",
    "start": 13.66,
    "end": 13.98
  },
  {
    "word": "بقواته",
    "start": 14.02,
    "end": 14.8
  },
  {
    "word": "الإسلامية",
    "start": 14.84,
    "end": 16.67
  },
  {
    "word": "نحو",
    "start": 16.77,
    "end": 17.07
  },
  {
    "word": "مدينة",
    "start": 17.13,
    "end": 17.61
  },
  {
    "word": "الحيرة",
    "start": 17.65,
    "end": 19.19
  },
  {
    "word": "وهي",
    "start": 19.31,
    "end": 19.53
  },
  {
    "word": "مدينة",
    "start": 19.61,
    "end": 20.03
  },
  {
    "word": "مشهورة",
    "start": 20.09,
    "end": 20.71
  },
  {
    "word": "بالثقافة",
    "start": 20.77,
    "end": 21.59
  },
  {
    "word": "والعلم",
    "start": 21.63,
    "end": 23.05
  },
  {
    "word": "وكانت",
    "start": 23.15,
    "end": 23.53
  },
  {
    "word": "عاصمة",
    "start": 23.61,
    "end": 24.15
  },
  {
    "word": "أل",
    "start": 24.19,
    "end": 24.37
  },
  {
    "word": "المنذر",
    "start": 24.41,
    "end": 25.27
  },
  {
    "word": "من",
    "start": 25.35,
    "end": 25.49
  },
  {
    "word": "النصارى",
    "start": 25.53,
    "end": 26.16
  },
  {
    "word": "العرب",
    "start": 26.3,
    "end": 27.38
  },
  {
    "word": "وتتبع",
    "start": 27.56,
    "end": 28.1
  },
  {
    "word": "للدولة",
    "start": 28.14,
    "end": 28.6
  },
  {
    "word": "الساسانية",
    "start": 28.64,
    "end": 30.04
  },
  {
    "word": "كانت",
    "start": 30.02,
    "end": 30.76
  },
  {
    "word": "الحيرة",
    "start": 30.8,
    "end": 31.34
  },
  {
    "word": "تتمتع",
    "start": 31.38,
    "end": 32.04
  },
  {
    "word": "بمكانة",
    "start": 32.08,
    "end": 32.74
  },
  {
    "word": "استراتيجية",
    "start": 32.78,
    "end": 33.82
  },
  {
    "word": "كبيرة",
    "start": 33.92,
    "end": 35.09
  },
  {
    "word": "فهي",
    "start": 35.27,
    "end": 35.59
  },
  {
    "word": "بوابة",
    "start": 35.65,
    "end": 36.21
  },
  {
    "word": "الفرات",
    "start": 36.25,
    "end": 36.67
  },
  {
    "word": "الأعلى",
    "start": 36.71,
    "end": 38.11
  },
  {
    "word": "ومن",
    "start": 38.29,
    "end": 38.57
  },
  {
    "word": "أخذها",
    "start": 38.61,
    "end": 39.21
  },
  {
    "word": "أمن",
    "start": 39.27,
    "end": 39.65
  },
  {
    "word": "الطريق",
    "start": 39.69,
    "end": 41.29
  },
  {
    "word": "نحو",
    "start": 41.41,
    "end": 41.71
  },
  {
    "word": "المدائن",
    "start": 41.73,
    "end": 42.4
  },
  {
    "word": "عاصمة",
    "start": 42.48,
    "end": 43.1
  },
  {
    "word": "الفرس",
    "start": 43.14,
    "end": 44.36
  },
  {
    "word": "فقام",
    "start": 44.46,
    "end": 45.0
  },
  {
    "word": "خالد",
    "start": 45.12,
    "end": 45.58
  },
  {
    "word": "بحصارها",
    "start": 45.64,
    "end": 46.52
  },
  {
    "word": "لعدة",
    "start": 46.58,
    "end": 47.1
  },
  {
    "word": "أيام",
    "start": 47.18,
    "end": 48.86
  },
  {
    "word": "ثم",
    "start": 48.96,
    "end": 49.27
  },
  {
    "word": "رأى",
    "start": 49.33,
    "end": 49.62
  },
  {
    "word": "أهلها",
    "start": 49.69,
    "end": 50.17
  },
  {
    "word": "أنهم",
    "start": 50.25,
    "end": 50.83
  },
  {
    "word": "لا",
    "start": 50.89,
    "end": 51.03
  },
  {
    "word": "قدرة",
    "start": 51.13,
    "end": 51.59
  },
  {
    "word": "لهم",
    "start": 51.63,
    "end": 51.93
  },
  {
    "word": "على",
    "start": 52.01,
    "end": 52.15
  },
  {
    "word": "المقاومة",
    "start": 52.19,
    "end": 53.67
  },
  {
    "word": "فطلبوا",
    "start": 53.91,
    "end": 54.33
  },
  {
    "word": "الصلح",
    "start": 54.49,
    "end": 54.99
  },
  {
    "word": "ودفع",
    "start": 55.01,
    "end": 55.43
  },
  {
    "word": "الجزية",
    "start": 55.47,
    "end": 56.52
  },
  {
    "word": "فقبل",
    "start": 56.8,
    "end": 57.38
  },
  {
    "word": "خالد",
    "start": 57.46,
    "end": 57.92
  },
  {
    "word": "ذلك",
    "start": 58.0,
    "end": 58.44
  },
  {
    "word": "وأمنهم",
    "start": 58.52,
    "end": 59.42
  },
  {
    "word": "على",
    "start": 59.52,
    "end": 59.8
  },
  {
    "word": "ديارهم",
    "start": 59.88,
    "end": 60.55
  },
  {
    "word": "وأنفسهم",
    "start": 60.65,
    "end": 62.53
  },
  {
    "word": "ولم",
    "start": 62.75,
    "end": 63.01
  },
  {
    "word": "تكن",
    "start": 63.09,
    "end": 63.41
  },
  {
    "word": "هناك",
    "start": 63.49,
    "end": 63.95
  },
  {
    "word": "معركة",
    "start": 64.03,
    "end": 64.61
  },
  {
    "word": "كبيرة",
    "start": 64.71,
    "end": 66.16
  },
  {
    "word": "بل",
    "start": 66.36,
    "end": 66.6
  },
  {
    "word": "دخلها",
    "start": 66.68,
    "end": 67.04
  },
  {
    "word": "المسلمون",
    "start": 67.08,
    "end": 67.78
  },
  {
    "word": "بالسلم",
    "start": 67.82,
    "end": 68.68
  },
  {
    "word": "وحسن",
    "start": 68.84,
    "end": 69.36
  },
  {
    "word": "التدبير",
    "start": 69.4,
    "end": 70.67
  },
  {
    "word": "وكان",
    "start": 70.85,
    "end": 71.27
  },
  {
    "word": "هذا",
    "start": 71.35,
    "end": 71.65
  },
  {
    "word": "الفتح",
    "start": 71.67,
    "end": 72.19
  },
  {
    "word": "نقطة",
    "start": 72.27,
    "end": 73.89
  },
  {
    "word": "تحول",
    "start": 73.97,
    "end": 74.75
  },
  {
    "word": "هامة",
    "start": 74.77,
    "end": 75.44
  },
  {
    "word": "في",
    "start": 75.54,
    "end": 75.68
  },
  {
    "word": "تمهيد",
    "start": 75.74,
    "end": 76.28
  },
  {
    "word": "طريق",
    "start": 76.36,
    "end": 76.76
  },
  {
    "word": "الفتوحات",
    "start": 76.8,
    "end": 77.76
  },
  {
    "word": "في",
    "start": 77.88,
    "end": 77.98
  },
  {
    "word": "العراق",
    "start": 78.0,
    "end": 79.08
  },
  {
    "word": "وبه",
    "start": 79.28,
    "end": 79.62
  },
  {
    "word": "ترسخ",
    "start": 79.7,
    "end": 80.34
  },
  {
    "word": "وجود",
    "start": 80.41,
    "end": 80.87
  },
  {
    "word": "المسلمين",
    "start": 80.91,
    "end": 82.11
  },
  {
    "word": "في",
    "start": 82.31,
    "end": 82.43
  },
  {
    "word": "المناطق",
    "start": 82.47,
    "end": 83.13
  },
  {
    "word": "المأهولة",
    "start": 83.17,
    "end": 84.07
  },
  {
    "word": "قرب",
    "start": 84.17,
    "end": 84.59
  },
  {
    "word": "عاصمة",
    "start": 84.61,
    "end": 85.25
  },
  {
    "word": "الفرس",
    "start": 85.3,
    "end": 86.1
  }
]